file_detector-1.0.1.dist-info/METADATA
file_detector-1.0.1.dist-info/RECORD
file_detector-1.0.1.dist-info/WHEEL
file_detector/__init__.py
file_detector/_file_detect.dylib
file_detector/detect.py
file_detector/magic.mgc