Metadata-Version: 2.1
Name: file_detector
Version: 1.0.1
Summary: File type detector
